obpgenerator/Contour.py
obpgenerator/Layer.py
obpgenerator/Part.py
obpgenerator/Shape.py
obpgenerator/__init__.py
obpgenerator/generate_obp.py
obpgenerator/layer_sorting.py
obpgenerator/manufacturing_settings.py
obpgenerator/shape_melting.py
obpgenerator/melt_strategies/__init__.py
obpgenerator/melt_strategies/line_melting.py
obpgenerator/melt_strategies/point_melting.py
obpgenerator/obpviewer/OBPCompiler.py
obpgenerator/obpviewer/obpviewer.py
obpgenerator/support_functions/__init__.py
obpgenerator/support_functions/file_import.py
obpgenerator/support_functions/generate_coordinates.py
obpgenerator/support_functions/offset_paths.py
obpgenerator/support_functions/slicer.py
obpgenerator/visualization/__init__.py
obpgenerator/visualization/obp_to_matplotlib.py
obpgenerator/visualization/visualization.py
obpgenerator-0.0.22.dist-info/LICENSE
obpgenerator-0.0.22.dist-info/METADATA
obpgenerator-0.0.22.dist-info/WHEEL
obpgenerator-0.0.22.dist-info/top_level.txt
obpgenerator-0.0.22.dist-info/RECORD
