Metadata-Version: 2.1
Name: obpgenerator
Version: 0.0.22
Summary: Generation of open beam path files based on different strategies
Home-page: https://github.com/wiberganton/obpgenerator
Author: Anton Wiberg
Author-email: wiberg.anton@gmail.com
Classifier: Programming Language :: Python :: 3
Classifier: License :: OSI Approved :: MIT License
Classifier: Operating System :: OS Independent
Requires-Python: >=3.7
License-File: LICENSE
Requires-Dist: svgpathtools
Requires-Dist: numpy
Requires-Dist: matplotlib
Requires-Dist: obplib
Requires-Dist: pyvista
Requires-Dist: shapely
